<?xml version="1.0" encoding="utf-8"?>
<config>
  <NextOrderId>52</NextOrderId>
  <NextDeliveryId>31</NextDeliveryId>
  <Clock>2025-03-07T18:05:00</Clock>
  <ManagerId>111111118</ManagerId>
  <ManagerPassword>nxnsj544bh@!</ManagerPassword>
  <CompanyAddress>קניון עזריאלי תל אביב</CompanyAddress>
  <Latitude>32.0747036</Latitude>
  <Longitude>34.7919705</Longitude>
  <MaxAirDistance>20</MaxAirDistance>
  <AvgCarSpeed>60</AvgCarSpeed>
  <AvgMotorcycleSpeed>80</AvgMotorcycleSpeed>
  <AvgBicycleSpeed>20</AvgBicycleSpeed>
  <AvgWalkSpeed>5</AvgWalkSpeed>
  <MaxDeliveryTime>04:00:00</MaxDeliveryTime>
  <RiskRange>00:30:00</RiskRange>
  <CourierInactivityTime>180.00:00:00</CourierInactivityTime>
</config>